uri_pathlib_factory/__init__.py
uri_pathlib_factory/main.py
uri_pathlib_factory/py.typed
uri_pathlib_factory-0.1.7.dist-info/LICENSE
uri_pathlib_factory-0.1.7.dist-info/METADATA
uri_pathlib_factory-0.1.7.dist-info/WHEEL
uri_pathlib_factory-0.1.7.dist-info/RECORD
