Metadata-Version: 2.1
Name: uri-pathlib-factory
Version: 0.1.7
Summary: A factory to instantiate Path's like object that are using Pathlib interface.
Home-page: https://github.com/petrus-v/uri-pathlib-factory
License: Apache Software License 2.0
Author: Pierre Verkest
Author-email: pierreverkest84@gmail.com
Requires-Python: >=3.7,<4.0
Classifier: Development Status :: 2 - Pre-Alpha
Classifier: Intended Audience :: Developers
Classifier: License :: Other/Proprietary License
Classifier: Natural Language :: English
Classifier: Operating System :: OS Independent
Classifier: Programming Language :: Python :: 3
Classifier: Programming Language :: Python :: 3.7
Classifier: Programming Language :: Python :: 3.8
Classifier: Programming Language :: Python :: 3.9
Classifier: Programming Language :: Python :: 3.10
Classifier: Programming Language :: Python :: 3.11
Classifier: Programming Language :: Python :: 3.12
Classifier: Topic :: Software Development :: Libraries
Provides-Extra: docs
Requires-Dist: Sphinx (>=5.0,<6.0) ; extra == "docs"
Requires-Dist: importlib-metadata (>=6.0,<7.0) ; python_version < "3.10"
Requires-Dist: myst-parser (>=0.18,<0.19) ; extra == "docs"
Requires-Dist: sphinx-rtd-theme (>=1.0,<2.0) ; extra == "docs"
Project-URL: Bug Tracker, https://github.com/petrus-v/uri-pathlib-factory/issues
Project-URL: Changelog, https://github.com/petrus-v/uri-pathlib-factory/blob/main/CHANGELOG.md
Project-URL: Documentation, https://uri-pathlib-factory.readthedocs.io
Project-URL: Repository, https://github.com/petrus-v/uri-pathlib-factory
